<profile>

<ReportVersion>
<Version>2019.2</Version>
</ReportVersion>

<UserAssignments>
<unit>ns</unit>
<ProductFamily>virtexuplus</ProductFamily>
<Part>xcu250-figd2104-2L-e</Part>
<TopModelName>conv_2d_cl_ss_ap_fixed_ap_fixed_16_4_5_3_0_config12_s</TopModelName>
<TargetClockPeriod>5.00</TargetClockPeriod>
<ClockUncertainty>0.62</ClockUncertainty>
</UserAssignments>

<PerformanceEstimates>
<PipelineType>none</PipelineType>
<SummaryOfTimingAnalysis>
<unit>ns</unit>
<EstimatedClockPeriod>4.299</EstimatedClockPeriod>
</SummaryOfTimingAnalysis>
<SummaryOfOverallLatency>
<unit>clock cycles</unit>
<Best-caseLatency>1216351</Best-caseLatency>
<Average-caseLatency>1299376</Average-caseLatency>
<Worst-caseLatency>1382176</Worst-caseLatency>
<Best-caseRealTimeLatency>6.082 ms</Best-caseRealTimeLatency>
<Average-caseRealTimeLatency>6.497 ms</Average-caseRealTimeLatency>
<Worst-caseRealTimeLatency>6.911 ms</Worst-caseRealTimeLatency>
<Interval-min>1216351</Interval-min>
<Interval-max>1382176</Interval-max>
</SummaryOfOverallLatency>
<SummaryOfLoopLatency>
<Conv2dWHLoop>
<TripCount>225</TripCount>
<Latency>
<range>
<min>1216350</min>
<max>1382175</max>
</range>
</Latency>
<IterationLatency>
<range>
<min>5406</min>
<max>6143</max>
</range>
</IterationLatency>
<Conv2dChanLoop>
<TripCount>64</TripCount>
<Latency>64</Latency>
<IterationLatency>1</IterationLatency>
</Conv2dChanLoop>
<Conv2dWHLoop.2>
<TripCount>576</TripCount>
<Latency>576</Latency>
<PipelineII>1</PipelineII>
<PipelineDepth>2</PipelineDepth>
</Conv2dWHLoop.2>
<Con2dCastLoop>
<TripCount>64</TripCount>
<Latency>128</Latency>
<IterationLatency>2</IterationLatency>
</Con2dCastLoop>
</Conv2dWHLoop>
</SummaryOfLoopLatency>
</PerformanceEstimates>

<AreaEstimates>
<Resources>
<BRAM_18K>41</BRAM_18K>
<DSP48E>64</DSP48E>
<FF>1707</FF>
<LUT>3586</LUT>
<URAM>0</URAM>
</Resources>
<AvailableResources>
<BRAM_18K>5376</BRAM_18K>
<DSP48E>12288</DSP48E>
<FF>3456000</FF>
<LUT>1728000</LUT>
<URAM>1280</URAM>
</AvailableResources>
</AreaEstimates>

<InterfaceSummary>
<RtlPorts>
<name>ap_clk</name>
<Object>conv_2d_cl_ss&lt;ap_fixed,ap_fixed&lt;16,4,5,3,0&gt;,config12&gt;</Object>
<Type>return value</Type>
<Scope></Scope>
<IOProtocol>ap_ctrl_hs</IOProtocol>
<IOConfig></IOConfig>
<Dir>in</Dir>
<Bits>1</Bits>
<Attribute>control</Attribute>
</RtlPorts>
<RtlPorts>
<name>ap_rst</name>
<Object>conv_2d_cl_ss&lt;ap_fixed,ap_fixed&lt;16,4,5,3,0&gt;,config12&gt;</Object>
<Type>return value</Type>
<Scope></Scope>
<IOProtocol>ap_ctrl_hs</IOProtocol>
<IOConfig></IOConfig>
<Dir>in</Dir>
<Bits>1</Bits>
<Attribute>control</Attribute>
</RtlPorts>
<RtlPorts>
<name>ap_start</name>
<Object>conv_2d_cl_ss&lt;ap_fixed,ap_fixed&lt;16,4,5,3,0&gt;,config12&gt;</Object>
<Type>return value</Type>
<Scope></Scope>
<IOProtocol>ap_ctrl_hs</IOProtocol>
<IOConfig></IOConfig>
<Dir>in</Dir>
<Bits>1</Bits>
<Attribute>control</Attribute>
</RtlPorts>
<RtlPorts>
<name>start_full_n</name>
<Object>conv_2d_cl_ss&lt;ap_fixed,ap_fixed&lt;16,4,5,3,0&gt;,config12&gt;</Object>
<Type>return value</Type>
<Scope></Scope>
<IOProtocol>ap_ctrl_hs</IOProtocol>
<IOConfig></IOConfig>
<Dir>in</Dir>
<Bits>1</Bits>
<Attribute>unknown</Attribute>
</RtlPorts>
<RtlPorts>
<name>ap_done</name>
<Object>conv_2d_cl_ss&lt;ap_fixed,ap_fixed&lt;16,4,5,3,0&gt;,config12&gt;</Object>
<Type>return value</Type>
<Scope></Scope>
<IOProtocol>ap_ctrl_hs</IOProtocol>
<IOConfig></IOConfig>
<Dir>out</Dir>
<Bits>1</Bits>
<Attribute>control</Attribute>
</RtlPorts>
<RtlPorts>
<name>ap_continue</name>
<Object>conv_2d_cl_ss&lt;ap_fixed,ap_fixed&lt;16,4,5,3,0&gt;,config12&gt;</Object>
<Type>return value</Type>
<Scope></Scope>
<IOProtocol>ap_ctrl_hs</IOProtocol>
<IOConfig></IOConfig>
<Dir>in</Dir>
<Bits>1</Bits>
<Attribute>control</Attribute>
</RtlPorts>
<RtlPorts>
<name>ap_idle</name>
<Object>conv_2d_cl_ss&lt;ap_fixed,ap_fixed&lt;16,4,5,3,0&gt;,config12&gt;</Object>
<Type>return value</Type>
<Scope></Scope>
<IOProtocol>ap_ctrl_hs</IOProtocol>
<IOConfig></IOConfig>
<Dir>out</Dir>
<Bits>1</Bits>
<Attribute>control</Attribute>
</RtlPorts>
<RtlPorts>
<name>ap_ready</name>
<Object>conv_2d_cl_ss&lt;ap_fixed,ap_fixed&lt;16,4,5,3,0&gt;,config12&gt;</Object>
<Type>return value</Type>
<Scope></Scope>
<IOProtocol>ap_ctrl_hs</IOProtocol>
<IOConfig></IOConfig>
<Dir>out</Dir>
<Bits>1</Bits>
<Attribute>control</Attribute>
</RtlPorts>
<RtlPorts>
<name>start_out</name>
<Object>conv_2d_cl_ss&lt;ap_fixed,ap_fixed&lt;16,4,5,3,0&gt;,config12&gt;</Object>
<Type>return value</Type>
<Scope></Scope>
<IOProtocol>ap_ctrl_hs</IOProtocol>
<IOConfig></IOConfig>
<Dir>out</Dir>
<Bits>1</Bits>
<Attribute>unknown</Attribute>
</RtlPorts>
<RtlPorts>
<name>start_write</name>
<Object>conv_2d_cl_ss&lt;ap_fixed,ap_fixed&lt;16,4,5,3,0&gt;,config12&gt;</Object>
<Type>return value</Type>
<Scope></Scope>
<IOProtocol>ap_ctrl_hs</IOProtocol>
<IOConfig></IOConfig>
<Dir>out</Dir>
<Bits>1</Bits>
<Attribute>unknown</Attribute>
</RtlPorts>
<RtlPorts>
<name>data_V_V_dout</name>
<Object>data_V_V</Object>
<Type>pointer</Type>
<Scope></Scope>
<IOProtocol>ap_fifo</IOProtocol>
<IOConfig></IOConfig>
<Dir>in</Dir>
<Bits>16</Bits>
<Attribute>control</Attribute>
</RtlPorts>
<RtlPorts>
<name>data_V_V_empty_n</name>
<Object>data_V_V</Object>
<Type>pointer</Type>
<Scope></Scope>
<IOProtocol>ap_fifo</IOProtocol>
<IOConfig></IOConfig>
<Dir>in</Dir>
<Bits>1</Bits>
<Attribute>control</Attribute>
</RtlPorts>
<RtlPorts>
<name>data_V_V_read</name>
<Object>data_V_V</Object>
<Type>pointer</Type>
<Scope></Scope>
<IOProtocol>ap_fifo</IOProtocol>
<IOConfig></IOConfig>
<Dir>out</Dir>
<Bits>1</Bits>
<Attribute>control</Attribute>
</RtlPorts>
<RtlPorts>
<name>res_V_V_din</name>
<Object>res_V_V</Object>
<Type>pointer</Type>
<Scope></Scope>
<IOProtocol>ap_fifo</IOProtocol>
<IOConfig></IOConfig>
<Dir>out</Dir>
<Bits>16</Bits>
<Attribute>control</Attribute>
</RtlPorts>
<RtlPorts>
<name>res_V_V_full_n</name>
<Object>res_V_V</Object>
<Type>pointer</Type>
<Scope></Scope>
<IOProtocol>ap_fifo</IOProtocol>
<IOConfig></IOConfig>
<Dir>in</Dir>
<Bits>1</Bits>
<Attribute>control</Attribute>
</RtlPorts>
<RtlPorts>
<name>res_V_V_write</name>
<Object>res_V_V</Object>
<Type>pointer</Type>
<Scope></Scope>
<IOProtocol>ap_fifo</IOProtocol>
<IOConfig></IOConfig>
<Dir>out</Dir>
<Bits>1</Bits>
<Attribute>control</Attribute>
</RtlPorts>
</InterfaceSummary>

</profile>
